django_rule_engine/__init__.py
django_rule_engine/apps.py
django_rule_engine/api/__init__.py
django_rule_engine/api/urls.py
django_rule_engine/api/views.py
django_rule_engine/fields/__init__.py
django_rule_engine/fields/rule_field.py
django_rule_engine/fields/rule_widget.py
django_rule_engine/fields/test_rule_field.py
django_rule_engine/static/rule_widget/codemirror-rule-engine.js
django_rule_engine/static/rule_widget/rule_widget.css
django_rule_engine/static/rule_widget/rule_widget.js
django_rule_engine/static/rule_widget/rule_widget_highlighting.css
django_rule_engine/templates/widgets/rule_widget.html
django_rule_engine-1.0.0.dist-info/licenses/LICENSE
django_rule_engine-1.0.0.dist-info/METADATA
django_rule_engine-1.0.0.dist-info/WHEEL
django_rule_engine-1.0.0.dist-info/top_level.txt
django_rule_engine-1.0.0.dist-info/RECORD
