Metadata-Version: 2.4
Name: django-rule-engine
Version: 1.0.0
Summary: Django field and widget for rule-engine with visual editor
Home-page: https://github.com/kelsoncm/django-rule-engine
Author: Kelson da Costa Medeiros
Author-email: Kelson da Costa Medeiros <kelsoncm@gmail.com>
License: MIT
Project-URL: Homepage, https://github.com/kelsoncm/django-rule-engine
Project-URL: Documentation, https://github.com/kelsoncm/django-rule-engine
Project-URL: Repository, https://github.com/kelsoncm/django-rule-engine
Project-URL: Issues, https://github.com/kelsoncm/django-rule-engine/issues
Keywords: django,rule-engine,rules,validation,field,widget
Classifier: Development Status :: 4 - Beta
Classifier: Environment :: Web Environment
Classifier: Framework :: Django
Classifier: Framework :: Django :: 4.2
Classifier: Framework :: Django :: 5.0
Classifier: Framework :: Django :: 5.1
Classifier: Framework :: Django :: 5.2
Classifier: Intended Audience :: Developers
Classifier: License :: OSI Approved :: MIT License
Classifier: Operating System :: OS Independent
Classifier: Programming Language :: Python
Classifier: Programming Language :: Python :: 3
Classifier: Programming Language :: Python :: 3.10
Classifier: Programming Language :: Python :: 3.11
Classifier: Programming Language :: Python :: 3.12
Classifier: Programming Language :: Python :: 3.13
Classifier: Programming Language :: Python :: 3.14
Classifier: Topic :: Internet :: WWW/HTTP
Classifier: Topic :: Internet :: WWW/HTTP :: Dynamic Content
Requires-Python: >=3.10
License-File: LICENSE
Requires-Dist: Django>=4.2
Requires-Dist: rule-engine>=4.5.3
Requires-Dist: django-json-widget>=2.0
Provides-Extra: dev
Requires-Dist: pytest>=7.0; extra == "dev"
Requires-Dist: pytest-django>=4.0; extra == "dev"
Requires-Dist: black>=23.0; extra == "dev"
Requires-Dist: flake8>=6.0; extra == "dev"
Requires-Dist: isort>=5.0; extra == "dev"
Dynamic: author
Dynamic: home-page
Dynamic: license-file
